odoo/addons/event_registration_cancel_reason/README.rst
odoo/addons/event_registration_cancel_reason/__init__.py
odoo/addons/event_registration_cancel_reason/__manifest__.py
odoo/addons/event_registration_cancel_reason/i18n/es.po
odoo/addons/event_registration_cancel_reason/i18n/event_registration_cancel_reason.pot
odoo/addons/event_registration_cancel_reason/models/__init__.py
odoo/addons/event_registration_cancel_reason/models/event_registration.py
odoo/addons/event_registration_cancel_reason/readme/CONFIGURE.rst
odoo/addons/event_registration_cancel_reason/readme/CONTRIBUTORS.rst
odoo/addons/event_registration_cancel_reason/readme/DESCRIPTION.rst
odoo/addons/event_registration_cancel_reason/readme/USAGE.rst
odoo/addons/event_registration_cancel_reason/security/ir.model.access.csv
odoo/addons/event_registration_cancel_reason/static/description/icon.png
odoo/addons/event_registration_cancel_reason/static/description/index.html
odoo/addons/event_registration_cancel_reason/tests/__init__.py
odoo/addons/event_registration_cancel_reason/tests/test_event_registration_cancel_reason.py
odoo/addons/event_registration_cancel_reason/views/event_registration_view.xml
odoo/addons/event_registration_cancel_reason/wizard/__init__.py
odoo/addons/event_registration_cancel_reason/wizard/event_registration_cancel_log_reason.py
odoo/addons/event_registration_cancel_reason/wizard/event_registration_cancel_log_reason_view.xml
odoo11_addon_event_registration_cancel_reason-11.0.1.0.0.99.dev6.dist-info/METADATA
odoo11_addon_event_registration_cancel_reason-11.0.1.0.0.99.dev6.dist-info/WHEEL
odoo11_addon_event_registration_cancel_reason-11.0.1.0.0.99.dev6.dist-info/top_level.txt
odoo11_addon_event_registration_cancel_reason-11.0.1.0.0.99.dev6.dist-info/RECORD
